JHVIT/JHVI_Tetra.py
JHVIT/__init__.py
JHVIT/mesh.py
JHVIT-0.0.14.dist-info/LICENSE.txt
JHVIT-0.0.14.dist-info/METADATA
JHVIT-0.0.14.dist-info/WHEEL
JHVIT-0.0.14.dist-info/top_level.txt
JHVIT-0.0.14.dist-info/RECORD
