Metadata-Version: 2.1
Name: JHVIT
Version: 0.0.14
Summary: Code to perform seismic hypocenter location on tetrahedral meshes
Home-page: https://github.com/groupeLIAMG/JHVIT.git
Author: Maher Nasr
Author-email: Maher.Nasr@inrs.ca
License: UNKNOWN
Keywords: joint hypocenter velocity inversion,hypocenter location,passive seismic,tetrahedral meshes
Platform: UNKNOWN
Classifier: Programming Language :: Python :: 3.7
Classifier: License :: OSI Approved :: MIT License
Classifier: Operating System :: OS Independent
Classifier: Intended Audience :: Science/Research
Classifier: Topic :: Scientific/Engineering
Requires-Python: ==3.7.*
Requires-Dist: numpy (>=1.20.1)
Requires-Dist: scipy
Requires-Dist: vtk
Requires-Dist: ttcrpy (>=1.1.8)
